mlx_transformers/__init__.py
mlx_transformers/models/__init__.py
mlx_transformers/models/base.py
mlx_transformers/models/bert.py
mlx_transformers/models/cache.py
mlx_transformers/models/clip.py
mlx_transformers/models/fuyu.py
mlx_transformers/models/llama.py
mlx_transformers/models/llava.py
mlx_transformers/models/m2m_100.py
mlx_transformers/models/modelling_outputs.py
mlx_transformers/models/openelm.py
mlx_transformers/models/persimmon.py
mlx_transformers/models/phi.py
mlx_transformers/models/phi3.py
mlx_transformers/models/roberta.py
mlx_transformers/models/t5.py
mlx_transformers/models/utils.py
mlx_transformers/models/xlm_roberta.py
mlx_transformers-0.1.5.dist-info/LICENSE
mlx_transformers-0.1.5.dist-info/METADATA
mlx_transformers-0.1.5.dist-info/WHEEL
mlx_transformers-0.1.5.dist-info/top_level.txt
mlx_transformers-0.1.5.dist-info/RECORD
