Metadata-Version: 2.1
Name: mlx-transformers
Version: 0.1.5
Summary: MLX transformers is a machine learning framework with similar Interface     to Huggingface transformers.
Home-page: https://github.com/ToluClassics/mlx-transformers
Author: Ogundepo Odunayo
Author-email: ogundepoodunayo@gmail.com
Classifier: Programming Language :: Python :: 3
Classifier: License :: OSI Approved :: MIT License
Requires-Python: >=3.10
License-File: LICENSE
Requires-Dist: huggingface-hub>=0.22.2
Requires-Dist: mlx>=0.8.1
Requires-Dist: numpy>=1.26.4
Requires-Dist: safetensors>=0.4.3
Requires-Dist: sentencepiece>=0.2.0
Requires-Dist: tokenizers>=0.19.1
Requires-Dist: torch>=2.2.2
Requires-Dist: tqdm>=4.66.2
Requires-Dist: transformers>=4.40.0
Requires-Dist: pillow==10.3.0
Requires-Dist: streamlit==1.34.0
